Workbook

Sheet Lisez-moi
A1: Fondamentaux Grasshopper – Référentiel des notions Magpie | D1: Fondamentaux Grasshopper – Ind. A – 25/08/2026
A3: Projet | B3: MAGPIE – outil d'exercices Grasshopper autocorrigés (RhinoForYou)
A4: Objet du document | B4: Référentiel unique des notions Rhino / Grasshopper à couvrir par les exercices Magpie, obtenu en fusionnant le tableau des fondamentaux V1 et l'intégralité du contenu des programmes de formation du catalogue.
A5: Indice | B5: Ind. A
A6: Date | B6: 25/08/2026
A7: Établi par | B7: Charles THIERRY DE VILLE D'AVRAY
A8: Document source remplacé | B8: Fondamentaux Grasshopper.xlsx (19 notions, 6 familles) – conservé sans modification
A9: Action de référence | B9: Compte rendu de session du 11/08/2026, §5.1 et §9.2 : « Comparer le tableau des fondamentaux aux programmes RhinoForYou débutant et perfectionnement ».
A11: SOURCES DÉPOUILLÉES
A12: D3 | B12: Grasshopper débutant 3 jours — Programme de formation Grasshopper débutant 3 jours.docx
A13: P3 | B13: Grasshopper perfectionnement 3 jours — Programme de formation Grasshopper perfectionnement 3 jours.docx
A14: P6 | B14: Grasshopper perfectionnement 6 jours — Programme de formation Grasshopper perfectionnement 6 jours.docx
A15: P6b | B15: Grasshopper perfectionnement 6 jours (1) — Programme de formation Grasshopper perfectionnement 6 jours (1).docx
A16: P6A | B16: Grasshopper perfectionnement 6 jours – Ind A – 27/02/2025 — Programme de formation Grasshopper perfectionnement 6 jours - IndA - 27-02-2025.docx
A17: RG8 | B17: Rhino – Grasshopper 8 jours — Programme de formation Grasshopper 8 jours.docx
A19: CONTENU DU CLASSEUR
A20: Référentiel | B20: Feuille principale. 116 lignes : 97 notions issues des programmes de formation + 19 fondamentaux Magpie V1, classés par domaine puis par catégorie.
A21: Fondamentaux V1 | B21: Reprise à l'identique du tableau d'origine (19 notions), pour traçabilité.
A22: Contenu programmes | B22: Relevé exhaustif et verbatim des 234 items des 6 programmes, dans l'ordre des documents, rattachés à une ligne du référentiel.
A23: Synthèse | B23: Comptages par domaine, niveau, mode de validation et programme ; analyse des écarts.
A24: Listes | B24: Listes de valeurs utilisées par les menus déroulants du référentiel.
A26: MÉTHODE
A27: 1 | B27: Extraction automatique de tous les paragraphes de liste des 6 programmes (234 occurrences).
A28: 2 | B28: Dédoublonnage par texte normalisé : 97 items distincts.
A29: 3 | B29: Classement de chaque item dans un domaine (10) et une catégorie, avec niveau et mode de validation proposés.
A30: 4 | B30: Intégration des 19 fondamentaux V1 et qualification de leur couverture par les programmes.
A31: 5 | B31: Construction de la matrice de couverture (une colonne par programme, valeur = jour · session).
A33: LÉGENDE — MODE DE VALIDATION
A34: ExactOrderedList | B34: Ordre des éléments significatif.
A35: SetEquality | B35: Ordre indifférent, ensemble attendu.
A36: SingleValue | B36: Une valeur unique attendue.
A37: NumericTolerance | B37: Valeur numérique avec marge d'erreur.
A38: GeometryTolerance | B38: Comparaison géométrique avec tolérance.
A39: Conceptuel (QCM) | B39: Notion non vérifiable par comparaison de résultat : question ciblée.
A41: LÉGENDE — ORIGINE
A42: Programme de formation | B42: Item présent dans au moins un programme du catalogue.
A43: Fondamentaux V1 – couverte | B43: Notion V1 explicitement traitée par un item de programme.
A44: Fondamentaux V1 – partielle | B44: Notion V1 incluse dans un item de programme plus large.
A45: Fondamentaux V1 – hors programmes | B45: Notion V1 absente des programmes : à arbitrer (ajout au programme ou exercice Magpie seul).
A47: POINTS À ARBITRER
A48: Écart principal | B48: Sur les 19 fondamentaux Magpie V1, 4 seulement sont explicitement couverts par les programmes, 5 le sont partiellement et 10 en sont totalement absents (types et conversion implicite, data matching, valeurs nulles, outils de texte, portes logiques).
A49: Doublon de source | B49: « perfectionnement 6 jours » et « perfectionnement 6 jours (1) » ont un contenu strictement identique ; l'indice A du 27/02/2025 y ajoute la rubrique « Utilisation des plugins » (11 items).
A50: Niveaux | B50: Les niveaux et modes de validation proposés sont une première affectation, à valider par Jérémy CAROLUS avant production des exercices.
A52: JOURNAL DES INDICES
A53: Indice | B53: Objet | C53: Date | D53: Auteur
A54: Ind. A | B54: Création. Fusion du tableau des fondamentaux V1 et de l'intégralité du contenu des 6 programmes de formation ; classement par domaine et catégorie ; matrice de couverture et analyse des écarts. | C54: 25/08/2026 | D54: C. THIERRY DE VILLE D'AVRAY

Sheet Référentiel
A1: Référentiel des notions – Rhino / Grasshopper | Y1: Fondamentaux Grasshopper – Ind. A – 25/08/2026
A3: N° | B3: ID | C3: Domaine | D3: Catégorie | E3: Notion | F3: Libellé source / description | G3: Niveau | H3: Origine / couverture | I3: D3 3 j débutant | J3: P3 3 j perf. | K3: P6 6 j perf. | L3: P6b 6 j perf. (1) | M3: P6A 6 j perf. Ind A | N3: RG8 8 j Rhino+GH | O3: Nb prog. | P3: Ordre V1 | Q3: Réf. croisée | R3: ValidationMode suggéré | S3: Type d'exercice | T3: Priorité de production | U3: Nb exercices Magpie prévus | V3: À réaliser par | W3: Statut | X3: Lien | Y3: Notes
A4: 1 | B4: PRG-074 | C4: 0 – Socle Rhino (prérequis) | D4: Interface et navigation Rhino | E4: Interface Rhino | F4: Présentation de l'interface utilisateur (barres d’outils, fenêtres, options). | G4: Débutant | H4: Programme de formation | N4: J1 | O4: 1 | R4: Conceptuel (QCM) | S4: QCM / question ciblée | T4: P0
A5: 2 | B5: PRG-075 | C5: 0 – Socle Rhino (prérequis) | D5: Interface et navigation Rhino | E5: Manipulation des vues | F5: Manipulation des vues | G5: Débutant | H5: Programme de formation | N5: J1 | O5: 1 | R5: Conceptuel (QCM) | S5: QCM / question ciblée | T5: P0
A6: 3 | B6: PRG-076 | C6: 0 – Socle Rhino (prérequis) | D6: Interface et navigation Rhino | E6: Navigation | F6: Outils de navigation : zoom, panoramique, rotation. | G6: Débutant | H6: Programme de formation | N6: J1 | O6: 1 | R6: Conceptuel (QCM) | S6: QCM / question ciblée | T6: P0
A7: 4 | B7: PRG-079 | C7: 0 – Socle Rhino (prérequis) | D7: Interface et navigation Rhino | E7: Sélection d'objets | F7: Sélection et manipulation d’objets | G7: Débutant | H7: Programme de formation | N7: J1 | O7: 1 | R7: Conceptuel (QCM) | S7: QCM / question ciblée | T7: P0
A8: 5 | B8: PRG-080 | C8: 0 – Socle Rhino (prérequis) | D8: Interface et navigation Rhino | E8: Groupes et blocs | F8: Groupes et blocs | G8: Débutant | H8: Programme de formation | N8: J1 | O8: 1 | R8: Conceptuel (QCM) | S8: QCM / question ciblée | T8: P0
A9: 6 | B9: PRG-081 | C9: 0 – Socle Rhino (prérequis) | D9: Interface et navigation Rhino | E9: Visibilité des objets | F9: Verrouillage et masquage d’objets, Isoler, Montrer) | G9: Débutant | H9: Programme de formation | N9: J1 | O9: 1 | R9: Conceptuel (QCM) | S9: QCM / question ciblée | T9: P0
A10: 7 | B10: PRG-077 | C10: 0 – Socle Rhino (prérequis) | D10: Modélisation Rhino | E10: Objets de base | F10: Création et manipulation d'objets de base (cubes, sphères, cylindres, etc.). | G10: Débutant | H10: Programme de formation | N10: J1 | O10: 1 | R10: GeometryTolerance | S10: Exercice Grasshopper | T10: P0
A11: 8 | B11: PRG-078 | C11: 0 – Socle Rhino (prérequis) | D11: Modélisation Rhino | E11: Transformations de base | F11: Transformation de base : déplacer, tourner, échelle, orienter | G11: Débutant | H11: Programme de formation | N11: J1 | O11: 1 | R11: GeometryTolerance | S11: Exercice Grasshopper | T11: P0
A12: 9 | B12: PRG-082 | C12: 0 – Socle Rhino (prérequis) | D12: Modélisation Rhino | E12: Courbes Rhino | F12: Création de courbes de différentes formes (lignes, cercles, ellipses, etc.). | G12: Débutant | H12: Programme de formation | N12: J1 | O12: 1 | R12: GeometryTolerance | S12: Exercice Grasshopper | T12: P0
A13: 10 | B13: PRG-083 | C13: 0 – Socle Rhino (prérequis) | D13: Modélisation Rhino | E13: Surfaces depuis courbes | F13: Utilisation de l’outil de courbes pour générer des surfaces. | G13: Débutant | H13: Programme de formation | N13: J1 | O13: 1 | R13: GeometryTolerance | S13: Exercice Grasshopper | T13: P0
A14: 11 | B14: PRG-084 | C14: 0 – Socle Rhino (prérequis) | D14: Modélisation Rhino | E14: Extrusion | F14: Extrusion et création de surfaces à partir de courbes. | G14: Débutant | H14: Programme de formation | N14: J1 | O14: 1 | R14: GeometryTolerance | S14: Exercice Grasshopper | T14: P0
A15: 12 | B15: PRG-085 | C15: 0 – Socle Rhino (prérequis) | D15: Modélisation Rhino | E15: Opérations booléennes Rhino | F15: Opérations booléennes (Union, intersection, et soustraction) | G15: Débutant | H15: Programme de formation | N15: J1 | O15: 1 | R15: GeometryTolerance | S15: Exercice Grasshopper | T15: P0
... A27: 24 | B27: PRG-097 | C27: 0 – Socle Rhino (prérequis) | D27: Préparation à l'impression 3D | E27: Export STL / OBJ | F27: Exportation des modèles 3D au format STL ou OBJ et paramètres d'exportation et optimisation des maillages pour réduire les erreurs d’impression. | G27: Débutant | H27: Programme de formation | N27: J2 | O27: 1 | R27: Conceptuel (QCM) | S27: Démonstration formateur | T27: P0
A28: 25 | B28: PRG-001 | C28: 1 – Environnement et principes Grasshopper | D28: Principes et interface Grasshopper | E28: Principes de la conception paramétrique | F28: Introduction à la conception paramétrique avec Grasshopper (Principes de la programmation visuelle) | G28: Débutant | H28: Programme de formation | I28: J1 | N28: J3 | O28: 2 | R28: Conceptuel (QCM) | S28: QCM / question ciblée | T28: P0
A29: 26 | B29: PRG-002 | C29: 1 – Environnement et principes Grasshopper | D29: Principes et interface Grasshopper | E29: Interopérabilité Rhino – Grasshopper | F29: Interopérabilité entre Grasshopper et Rhino (Bake et Geometry Pipeline) | G29: Débutant | H29: Programme de formation | I29: J1 | N29: J3 | O29: 2 | R29: GeometryTolerance | S29: Exercice Grasshopper | T29: P0
A30: 27 | B30: PRG-003 | C30: 1 – Environnement et principes Grasshopper | D30: Principes et interface Grasshopper | E30: Flux de données et câblage | F30: La logique de Grasshopper (Curseurs, données d’entrée, panel, données de sortie, branchement des câbles… ) | G30: Débutant | H30: Programme de formation | I30: J1 | N30: J3 | O30: 2 | R30: SingleValue | S30: Exercice Grasshopper | T30: P0
A31: 28 | B31: PRG-004 | C31: 1 – Environnement et principes Grasshopper | D31: Principes et interface Grasshopper | E31: Interface et canvas | F31: L’environnement et l’interface de Grasshopper (Barre d’outils et navigation dans le Canvas) | G31: Débutant | H31: Programme de formation | I31: J1 | N31: J3 | O31: 2 | R31: Conceptuel (QCM) | S31: QCM / question ciblée | T31: P0
A32: 29 | B32: PRG-063 | C32: 1 – Environnement et principes Grasshopper | D32: Écosystème de plugins | E32: Installation de plugins – Food4Rhino | F32: Installer un plugin à partir d’un fichier gha ou exe téléchargé sur food4rhino | G32: Intermédiaire | H32: Programme de formation | M32: J2·S3 | O32: 1 | R32: Conceptuel (QCM) | S32: Démonstration formateur | T32: P1
A33: 30 | B33: PRG-064 | C33: 1 – Environnement et principes Grasshopper | D33: Écosystème de plugins | E33: Installation de plugins – Package Manager | F33: Installer un plugin depuis le package manager | G33: Intermédiaire | H33: Programme de formation | M33: J2·S3 | O33: 1 | R33: Conceptuel (QCM) | S33: Démonstration formateur | T33: P1
A34: 31 | B34: PRG-065 | C34: 1 – Environnement et principes Grasshopper | D34: Écosystème de plugins | E34: Plugins d'ergonomie – principe | F34: Customisation de l’interface avec des plugins d’ergonomie ; | G34: Intermédiaire | H34: Programme de formation | M34: J2·S3 | O34: 1 | R34: Conceptuel (QCM) | S34: QCM / question ciblée | T34: P1
A35: 32 | B35: PRG-066 | C35: 1 – Environnement et principes Grasshopper | D35: Écosystème de plugins | E35: Plugin Bifocals | F35: Bifocals : Ajoute des étiquettes flottantes au-dessus des composants pour rendre l'interface plus lisible. | G35: Intermédiaire | H35: Programme de formation | M35: J2·S3 | O35: 1 | R35: Conceptuel (QCM) | S35: Démonstration formateur | T35: P1
A36: 33 | B36: PRG-067 | C36: 1 – Environnement et principes Grasshopper | D36: Écosystème de plugins | E36: Plugin SnappingGecko | F36: SnappingGecko : pour aimanter les composants les uns aux autres horizontalement ou verticalement, facilite le rangement | G36: Intermédiaire | H36: Programme de formation | M36: J2·S3 | O36: 1 | R36: Conceptuel (QCM) | S36: Démonstration formateur | T36: P1
A37: 34 | B37: PRG-068 | C37: 1 – Environnement et principes Grasshopper | D37: Écosystème de plugins | E37: Plugin Palette | F37: Palette : Changer les couleurs de l’interface Grasshopper | G37: Intermédiaire | H37: Programme de formation | M37: J2·S3 | O37: 1 | R37: Conceptuel (QCM) | S37: Démonstration formateur | T37: P1
A38: 35 | B38: PRG-069 | C38: 1 – Environnement et principes Grasshopper | D38: Écosystème de plugins | E38: Plugin Moonlight | F38: Moonlight : Ajoute un mode sombre à l’interface | G38: Intermédiaire | H38: Programme de formation | M38: J2·S3 | O38: 1 | R38: Conceptuel (QCM) | S38: Démonstration formateur | T38: P1
A39: 36 | B39: PRG-070 | C39: 1 – Environnement et principes Grasshopper | D39: Écosystème de plugins | E39: Plugin pOd | F39: pOd : pour afficher la vue Rhino sur le canvas Grasshopper | G39: Intermédiaire | H39: Programme de formation | M39: J2·S3 | O39: 1 | R39: Conceptuel (QCM) | S39: Démonstration formateur | T39: P1
A40: 37 | B40: PRG-071 | C40: 1 – Environnement et principes Grasshopper | D40: Écosystème de plugins | E40: Plugin AutoGraph | F40: AutoGraph : pour ranger automatiquement la definition et “déméler les “fils” entre les composants | G40: Intermédiaire | H40: Programme de formation | M40: J2·S3 | O40: 1 | R40: Conceptuel (QCM) | S40: Démonstration formateur | T40: P1
A41: 38 | B41: PRG-072 | C41: 1 – Environnement et principes Grasshopper | D41: Écosystème de plugins | E41: Plugins fonctionnels – principe | F41: Plugins essentiels couramment utilisés pour ajouter des fonctions à Grasshopper : | G41: Intermédiaire | H41: Programme de formation | M41: J2·S3 | O41: 1 | R41: Conceptuel (QCM) | S41: QCM / question ciblée | T41: P1
A42: 39 | B42: PRG-073 | C42: 1 – Environnement et principes Grasshopper | D42: Écosystème de plugins | E42: Plugins fonctionnels essentiels | F42: Metahopper, Human, Elefront, Weaverbird, Pufferfish, LunchBox | G42: Intermédiaire | H42: Programme de formation | M42: J2·S3 | O42: 1 | R42: Conceptuel (QCM) | S42: QCM / question ciblée | T42: P1
A43: 40 | B43: FND-01 | C43: 2 – Données et logique | D43: Types et conversion implicite | E43: Types de base et conversion implicite | F43: Comportement d'un flux de données (Number, Integer, Text, Boolean, Point...) quand il est accepté implicitement par un composant attendant un autre type (ex : slider → integer). | G43: Débutant | H43: Fondamentaux V1 – hors programmes (à ajouter) | P43: 1 | R43: SingleValue | S43: Exercice Grasshopper | T43: P0 | Y43: Notion issue du tableau des fondamentaux Magpie V1. Aucun item de programme correspondant.
A44: 41 | B44: FND-02 | C44: 2 – Données et logique | D44: Types et conversion implicite | E44: Échec de conversion et valeurs invalides | F44: Ce qui se produit quand une conversion implicite échoue (texte non numérique vers un input numérique, etc.) : message d'erreur, valeur nulle, composant en échec. | G44: Intermédiaire | H44: Fondamentaux V1 – hors programmes (à ajouter) | P44: 2 | R44: SingleValue | S44: Exercice Grasshopper | T44: P1 | Y44: Notion issue du tableau des fondamentaux Magpie V1. Aucun item de programme correspondant.
A45: 42 | B45: FND-03 | C45: 2 – Données et logique | D45: Listes | E45: Item, liste et indexation (0-based) | F45: Différence entre un item unique et une liste, lecture d'un élément à un index donné (List Item), indexation négative. | G45: Débutant | H45: Fondamentaux V1 – couverte par les programmes | P45: 3 | Q45: PRG-017 | R45: SingleValue | S45: Exercice Grasshopper | T45: P0 | Y45: Notion issue du tableau des fondamentaux Magpie V1. Rapprochement programme : PRG-017
A46: 43 | B46: FND-04 | C46: 2 – Données et logique | D46: Listes | E46: Longueur et génération de séries | F46: Comptage d'une liste (List Length) et génération de séquences numériques (Series, Range). | G46: Débutant | H46: Fondamentaux V1 – couverture partielle | P46: 4 | Q46: PRG-017 | R46: ExactOrderedList | S46: Exercice Grasshopper | T46: P0 | Y46: Notion issue du tableau des fondamentaux Magpie V1. Rapprochement programme : PRG-017
A47: 44 | B47: FND-07 | C47: 2 – Données et logique | D47: Listes | E47: Tri (Sort List, Sort Text) | F47: Réordonnancement d'une liste selon une clé de tri, avec ou sans liste secondaire liée. | G47: Débutant | H47: Fondamentaux V1 – couverte par les programmes | P47: 7 | Q47: PRG-017 | R47: ExactOrderedList | S47: Exercice Grasshopper | T47: P0 | Y47: Notion issue du tableau des fondamentaux Magpie V1. Rapprochement programme : PRG-017
A48: 45 | B48: FND-08 | C48: 2 – Données et logique | D48: Listes | E48: Filtrage et suppression (Cull Pattern, Dispatch) | F48: Élimination ou séparation d'éléments d'une liste selon un motif booléen répétitif. | G48: Intermédiaire | H48: Fondamentaux V1 – couverture partielle | P48: 8 | Q48: PRG-017 | R48: SetEquality | S48: Exercice Grasshopper | T48: P1 | Y48: Notion issue du tableau des fondamentaux Magpie V1. Rapprochement programme : PRG-017
A49: 46 | B49: FND-09 | C49: 2 – Données et logique | D49: Listes | E49: Décalage et permutation (Shift List, Reverse List) | F49: Rotation, décalage circulaire et inversion de l'ordre des éléments d'une liste. | G49: Intermédiaire | H49: Fondamentaux V1 – couverture partielle | P49: 9 | Q49: PRG-017 | R49: ExactOrderedList | S49: Exercice Grasshopper | T49: P1 | Y49: Notion issue du tableau des fondamentaux Magpie V1. Rapprochement programme : PRG-017
A50: 47 | B50: PRG-017 | C50: 2 – Données et logique | D50: Listes | E50: Listes – traitement et tri | F50: Outils de traitement des Listes, fonctions de tri par ordre croissant et décroissant | G50: Débutant | H50: Programme de formation | I50: J3 | K50: J1·S1 | L50: J1·S1 | M50: J1·S1 | N50: J5 | O50: 5 | R50: ExactOrderedList | S50: Exercice Grasshopper | T50: P0
A51: 48 | B51: FND-11 | C51: 2 – Données et logique | D51: Arbres de données | E51: Branche et chemin (path) | F51: Structure d'un arbre de données : notion de branche, de chemin ({0;0;1}) et de correspondance avec une liste imbriquée. | G51: Intermédiaire | H51: Fondamentaux V1 – couverte par les programmes | P51: 11 | Q51: PRG-018 | R51: SingleValue | S51: Exercice Grasshopper | T51: P1 | Y51: Notion issue du tableau des fondamentaux Magpie V1. Rapprochement programme : PRG-018
A52: 49 | B52: FND-12 | C52: 2 – Données et logique | D52: Arbres de données | E52: Graft et Flatten | F52: Transformation d'une structure de données : éclatement d'une liste en branches individuelles (Graft) et aplatissement d'un arbre en une seule liste (Flatten). | G52: Intermédiaire | H52: Fondamentaux V1 – couverte par les programmes | P52: 12 | Q52: PRG-024 | R52: SetEquality | S52: Exercice Grasshopper | T52: P1 | Y52: Notion issue du tableau des fondamentaux Magpie V1. Rapprochement programme : PRG-024
A53: 50 | B53: FND-13 | C53: 2 – Données et logique | D53: Arbres de données | E53: Simplify et Trim Tree | F53: Nettoyage de la structure d'un arbre : suppression des niveaux de branche redondants. | G53: Intermédiaire | H53: Fondamentaux V1 – couverture partielle | P53: 13 | Q53: PRG-024 | R53: SetEquality | S53: Exercice Grasshopper | T53: P1 | Y53: Notion issue du tableau des fondamentaux Magpie V1. Rapprochement programme : PRG-024
A54: 51 | B54: PRG-018 | C54: 2 – Données et logique | D54: Arbres de données | E54: Arbres – construction et lecture | F54: Création et lecture d’un arbre de données et numérotation des branches | G54: Intermédiaire | H54: Programme de formation | I54: J3 | K54: J1·S1 | L54: J1·S1 | M54: J1·S1 | N54: J5 | O54: 5 | R54: SetEquality | S54: Exercice Grasshopper | T54: P1
A55: 52 | B55: PRG-024 | C55: 2 – Données et logique | D55: Arbres de données | E55: Arbres – Graft et Flatten | F55: Approfondir les listes et arbres de données (créer un arbre de données, lire dans un arbre de données, Graft et Flatten) | G55: Intermédiaire | H55: Programme de formation | J55: J1 | K55: J1·S1 | L55: J1·S1 | M55: J1·S1 | N55: J5 | O55: 5 | R55: SetEquality | S55: Exercice Grasshopper | T55: P1
A56: 53 | B56: FND-05 | C56: 2 – Données et logique | D56: Comportements implicites | E56: Data Matching par défaut (shortest list) | F56: Comportement automatique de Grasshopper quand deux listes de tailles différentes entrent dans un même composant : troncature implicite sur la plus courte. | G56: Intermédiaire | H56: Fondamentaux V1 – hors programmes (à ajouter) | P56: 5 | R56: ExactOrderedList | S56: Exercice Grasshopper | T56: P1 | Y56: Notion issue du tableau des fondamentaux Magpie V1. Aucun item de programme correspondant.
A57: 54 | B57: FND-06 | C57: 2 – Données et logique | D57: Comportements implicites | E57: Data Matching explicite (Longest List, Cross Reference) | F57: Bascule volontaire entre les modes de correspondance (clic droit sur le composant) et conséquences sur le résultat produit. | G57: Intermédiaire | H57: Fondamentaux V1 – hors programmes (à ajouter) | P57: 6 | R57: ExactOrderedList | S57: Exercice Grasshopper | T57: P1 | Y57: Notion issue du tableau des fondamentaux Magpie V1. Aucun item de programme correspondant.
A58: 55 | B58: FND-10 | C58: 2 – Données et logique | D58: Comportements implicites | E58: Valeurs nulles / vides dans une liste | F58: Propagation silencieuse des valeurs null à travers les composants et impact sur les calculs en aval. | G58: Intermédiaire | H58: Fondamentaux V1 – hors programmes (à ajouter) | P58: 10 | R58: SetEquality | S58: Exercice Grasshopper | T58: P1 | Y58: Notion issue du tableau des fondamentaux Magpie V1. Aucun item de programme correspondant.
A59: 56 | B59: FND-14 | C59: 2 – Données et logique | D59: Comportements implicites | E59: Recalcul automatique et ordre d'évaluation | F59: Logique de mise à jour du canvas : recalcul en cascade à la modification d'une entrée, notion de dépendance entre composants (conceptuel, à valider via question ciblée plutôt que comparaison de résultat). | G59: Intermédiaire | H59: Fondamentaux V1 – couverture partielle | P59: 14 | Q59: PRG-027 | R59: SingleValue (conceptuel) | S59: Exercice Grasshopper | T59: P1 | Y59: Notion issue du tableau des fondamentaux Magpie V1. Rapprochement programme : PRG-027
A60: 57 | B60: FND-15 | C60: 2 – Données et logique | D60: Outils de texte | E60: Concaténation et construction de chaînes | F60: Assemblage de plusieurs éléments en une seule chaîne de caractères (Concatenate, Text Join) avec ou sans séparateur. | G60: Débutant | H60: Fondamentaux V1 – hors programmes (à ajouter) | P60: 15 | R60: SingleValue | S60: Exercice Grasshopper | T60: P0 | Y60: Notion issue du tableau des fondamentaux Magpie V1. Aucun item de programme correspondant.
A61: 58 | B61: FND-16 | C61: 2 – Données et logique | D61: Outils de texte | E61: Manipulation de texte | F61: Opérations courantes sur une chaîne : découpe (Split), remplacement (Replace), nettoyage (Trim), casse (Upper/Lower). | G61: Intermédiaire | H61: Fondamentaux V1 – hors programmes (à ajouter) | P61: 16 | R61: SingleValue | S61: Exercice Grasshopper | T61: P1 | Y61: Notion issue du tableau des fondamentaux Magpie V1. Aucun item de programme correspondant.
A62: 59 | B62: FND-17 | C62: 2 – Données et logique | D62: Portes logiques | E62: Booléens et comparaisons | F62: Production d'une valeur booléenne à partir d'une comparaison (Equality, Larger Than, Smaller Than). | G62: Débutant | H62: Fondamentaux V1 – hors programmes (à ajouter) | P62: 17 | R62: SingleValue | S62: Exercice Grasshopper | T62: P0 | Y62: Notion issue du tableau des fondamentaux Magpie V1. Aucun item de programme correspondant.
A63: 60 | B63: FND-18 | C63: 2 – Données et logique | D63: Portes logiques | E63: Opérateurs logiques combinés | F63: Combinaison de plusieurs conditions (And, Or, Not, Logic Gate) pour produire un résultat booléen unique. | G63: Intermédiaire | H63: Fondamentaux V1 – hors programmes (à ajouter) | P63: 18 | R63: SingleValue | S63: Exercice Grasshopper | T63: P1 | Y63: Notion issue du tableau des fondamentaux Magpie V1. Aucun item de programme correspondant.
A64: 61 | B64: FND-19 | C64: 2 – Données et logique | D64: Portes logiques | E64: Structure conditionnelle | F64: Utilisation d'une condition pour orienter un résultat ou filtrer une liste (If, Stream Filter, Dispatch piloté par condition). | G64: Intermédiaire | H64: Fondamentaux V1 – hors programmes (à ajouter) | P64: 19 | R64: SetEquality | S64: Exercice Grasshopper | T64: P1 | Y64: Notion issue du tableau des fondamentaux Magpie V1. Aucun item de programme correspondant.
A65: 62 | B65: PRG-005 | C65: 3 – Géométrie paramétrique | D65: Géométrie vectorielle et filaire | E65: Géométrie vectorielle | F65: Création d’éléments de construction vectoriels (Points, vecteurs, plans) | G65: Débutant | H65: Programme de formation | I65: J1 | N65: J3 | O65: 2 | R65: GeometryTolerance | S65: Exercice Grasshopper | T65: P0
A66: 63 | B66: PRG-006 | C66: 3 – Géométrie paramétrique | D66: Géométrie vectorielle et filaire | E66: Géométrie filaire | F66: Création de géométrie filaire (Cercles, carrés, Polygones, Courbes…) | G66: Débutant | H66: Programme de formation | I66: J1 | N66: J3 | O66: 2 | R66: GeometryTolerance | S66: Exercice Grasshopper | T66: P0
A67: 64 | B67: PRG-007 | C67: 3 – Géométrie paramétrique | D67: Géométrie vectorielle et filaire | E67: Division de courbes | F67: Les outils de division de courbes | G67: Débutant | H67: Programme de formation | I67: J1 | N67: J3 | O67: 2 | R67: GeometryTolerance | S67: Exercice Grasshopper | T67: P0
A68: 65 | B68: PRG-008 | C68: 3 – Géométrie paramétrique | D68: Plan paramétrique | E68: Dessin paramétrique 2D | F68: Exercice d’application sur un dessin paramétrique 2D | G68: Débutant | H68: Programme de formation | I68: J1 | N68: J3 | O68: 2 | R68: GeometryTolerance | S68: Exercice de synthèse | T68: P0
A69: 66 | B69: PRG-009 | C69: 3 – Géométrie paramétrique | D69: Plan paramétrique | E69: Cotation automatique | F69: Génération des cotations automatique | G69: Débutant | H69: Programme de formation | I69: J1 | N69: J3 | O69: 2 | R69: SetEquality | S69: Exercice Grasshopper | T69: P0
A70: 67 | B70: PRG-010 | C70: 3 – Géométrie paramétrique | D70: Transformations et réseaux | E70: Transformations | F70: Les outils de transformation (matrice linéaire, polaire, rotation , symétrie…) | G70: Débutant | H70: Programme de formation | I70: J2 | N70: J4 | O70: 2 | R70: GeometryTolerance | S70: Exercice Grasshopper | T70: P0
A71: 68 | B71: PRG-011 | C71: 3 – Géométrie paramétrique | D71: Transformations et réseaux | E71: Matrices rectangulaires et polaires | F71: Les matrices rectangulaires et polaires | G71: Débutant | H71: Programme de formation | I71: J2 | N71: J4 | O71: 2 | R71: GeometryTolerance | S71: Exercice Grasshopper | T71: P0
A72: 69 | B72: PRG-012 | C72: 3 – Géométrie paramétrique | D72: Surfaces et solides | E72: Surfaces | F72: Création de géométrie surfacique (balayage, surface par section…) | G72: Débutant | H72: Programme de formation | I72: J2 | N72: J4 | O72: 2 | R72: GeometryTolerance | S72: Exercice Grasshopper | T72: P0
A73: 70 | B73: PRG-013 | C73: 3 – Géométrie paramétrique | D73: Surfaces et solides | E73: Solides fermés | F73: Comment boucher les trous d’une polysurface pour former un solide fermé | G73: Débutant | H73: Programme de formation | I73: J2 | N73: J4 | O73: 2 | R73: SingleValue | S73: Exercice Grasshopper | T73: P0
A74: 71 | B74: PRG-014 | C74: 3 – Géométrie paramétrique | D74: Surfaces et solides | E74: Intersections entre solides | F74: Recherche d’intersection entre différentes géométries | G74: Débutant | H74: Programme de formation | I74: J2 | N74: J4 | O74: 2 | R74: GeometryTolerance | S74: Exercice Grasshopper | T74: P0
A75: 72 | B75: PRG-015 | C75: 3 – Géométrie paramétrique | D75: Surfaces et solides | E75: Détection de collisions | F75: Détection de collisions | G75: Débutant | H75: Programme de formation | I75: J2 | N75: J4 | O75: 2 | R75: SetEquality | S75: Exercice Grasshopper | T75: P0
A76: 73 | B76: PRG-016 | C76: 3 – Géométrie paramétrique | D76: Synthèse géométrie | E76: Modèle 3D paramétrique | F76: Exercice d’application sur un modèle 3D paramétrique | G76: Débutant | H76: Programme de formation | I76: J2 | N76: J4 | O76: 2 | R76: GeometryTolerance | S76: Exercice de synthèse | T76: P0
A77: 74 | B77: PRG-049 | C77: 3 – Géométrie paramétrique | D77: Maillages et SubD | E77: Maillages – génération | F77: Générer des Maillages avec Weaverbird | G77: Perfectionnement | H77: Programme de formation | K77: J5·S9 | L77: J5·S9 | M77: J5·S9 | O77: 3 | R77: GeometryTolerance | S77: Exercice Grasshopper | T77: P2
A78: 75 | B78: PRG-050 | C78: 3 – Géométrie paramétrique | D78: Maillages et SubD | E78: Maillages – lissage | F78: Adoucir un maillage | G78: Perfectionnement | H78: Programme de formation | K78: J5·S9 | L78: J5·S9 | M78: J5·S9 | O78: 3 | R78: GeometryTolerance | S78: Exercice Grasshopper | T78: P2
A79: 76 | B79: PRG-051 | C79: 3 – Géométrie paramétrique | D79: Maillages et SubD | E79: Maillages – réparation | F79: Réparer un maillages avec Mesh+ | G79: Perfectionnement | H79: Programme de formation | K79: J5·S9 | L79: J5·S9 | M79: J5·S9 | O79: 3 | R79: GeometryTolerance | S79: Exercice Grasshopper | T79: P2
A80: 77 | B80: PRG-052 | C80: 3 – Géométrie paramétrique | D80: Maillages et SubD | E80: SubD – génération | F80: Générer une surface SubD à partir d’un maillage | G80: Perfectionnement | H80: Programme de formation | K80: J5·S9 | L80: J5·S9 | M80: J5·S9 | O80: 3 | R80: GeometryTolerance | S80: Exercice Grasshopper | T80: P2
A81: 78 | B81: PRG-053 | C81: 3 – Géométrie paramétrique | D81: Maillages et SubD | E81: SubD – déformation | F81: Déformer une surface SubD à partir d’un squelette | G81: Perfectionnement | H81: Programme de formation | K81: J5·S9 | L81: J5·S9 | M81: J5·S9 | O81: 3 | R81: GeometryTolerance | S81: Exercice Grasshopper | T81: P2
A82: 79 | B82: PRG-019 | C82: 4 – Mesures, quantitatifs et export | D82: Mesures géométriques | E82: Mesures dimensionnelles | F82: Outils de mesure (Longueurs, Aires, Volumes) | G82: Débutant | H82: Programme de formation | I82: J3 | K82: J1·S1 | L82: J1·S1 | M82: J1·S1 | N82: J5 | O82: 5 | R82: NumericTolerance | S82: Exercice Grasshopper | T82: P0
A83: 80 | B83: PRG-020 | C83: 4 – Mesures, quantitatifs et export | D83: Mesures géométriques | E83: Rayon et courbure | F83: Mesure de rayon et courbure | G83: Débutant | H83: Programme de formation | I83: J3 | K83: J1·S1 | L83: J1·S1 | M83: J1·S1 | N83: J5 | O83: 5 | R83: NumericTolerance | S83: Exercice Grasshopper | T83: P0
A84: 81 | B84: PRG-021 | C84: 4 – Mesures, quantitatifs et export | D84: Mesures géométriques | E84: Centre de gravité | F84: Recherche d’un centre de gravité | G84: Débutant | H84: Programme de formation | I84: J3 | K84: J1·S1 | L84: J1·S1 | M84: J1·S1 | N84: J5 | O84: 5 | R84: NumericTolerance | S84: Exercice Grasshopper | T84: P0
A85: 82 | B85: PRG-022 | C85: 4 – Mesures, quantitatifs et export | D85: Quantitatifs et chiffrage | E85: Métrés | F85: Exercice d’application sur un calcul de métrés | G85: Intermédiaire | H85: Programme de formation | I85: J3 | K85: J1·S2 | L85: J1·S2 | M85: J1·S2 | N85: J5 | O85: 5 | R85: NumericTolerance | S85: Exercice de synthèse | T85: P1
A86: 83 | B86: PRG-023 | C86: 4 – Mesures, quantitatifs et export | D86: Quantitatifs et chiffrage | E86: Chiffrage et devis | F86: Exercice d’application sur un devis généré à partir d’un modèle 3D grasshopper | G86: Intermédiaire | H86: Programme de formation | I86: J3 | K86: J1·S2 | L86: J1·S2 | M86: J1·S2 | N86: J5 | O86: 5 | R86: NumericTolerance | S86: Exercice de synthèse | T86: P1
A87: 84 | B87: PRG-036 | C87: 4 – Mesures, quantitatifs et export | D87: Quantitatifs et chiffrage | E87: Comptage de quantités | F87: Comptage automatique des quantités de blocs | G87: Intermédiaire | H87: Programme de formation | K87: J1·S1 | L87: J1·S1 | M87: J1·S1 | O87: 3 | R87: SingleValue | S87: Exercice Grasshopper | T87: P1
A88: 85 | B88: PRG-037 | C88: 4 – Mesures, quantitatifs et export | D88: Export de données | E88: Préparation de données tabulaires | F88: Préparation des données des colonnes dans Grasshopper | G88: Intermédiaire | H88: Programme de formation | K88: J1·S2 | L88: J1·S2 | M88: J1·S2 | O88: 3 | R88: ExactOrderedList | S88: Exercice Grasshopper | T88: P1
A89: 86 | B89: PRG-038 | C89: 4 – Mesures, quantitatifs et export | D89: Export de données | E89: Export Excel | F89: Export d’un tableau de données vers EXCEL dans une feuille de calcul | G89: Intermédiaire | H89: Programme de formation | K89: J1·S2 | L89: J1·S2 | M89: J1·S2 | O89: 3 | R89: Conceptuel (QCM) | S89: Démonstration formateur | T89: P1
A90: 87 | B90: PRG-039 | C90: 4 – Mesures, quantitatifs et export | D90: Export de données | E90: Export CSV / nomenclature | F90: Export d’une nomenclature au format CSV à partir de Grasshopper | G90: Intermédiaire | H90: Programme de formation | K90: J1·S2 | L90: J1·S2 | M90: J1·S2 | O90: 3 | R90: Conceptuel (QCM) | S90: Démonstration formateur | T90: P1
A91: 88 | B91: PRG-025 | C91: 5 – Méthode, performance et évènements | D91: Organisation et performance | E91: Organisation et lisibilité | F91: Apprendre une méthode d’organisation et de rangement du code pour optimiser la vitesse de développement (Clusters, Nommage des paramètres d’entrée et de sortie, Groupes, titres) | G91: Intermédiaire | H91: Programme de formation | J91: J1 | K91: J2·S3 | L91: J2·S3 | M91: J2·S3 | N91: J6 | O91: 5 | R91: Conceptuel (QCM) | S91: QCM / question ciblée | T91: P1
A92: 89 | B92: PRG-026 | C92: 5 – Méthode, performance et évènements | D92: Organisation et performance | E92: Performance d'exécution | F92: Optimiser la vitesse d’exécution d’une définition Grasshopper ( Multiprocessing, analyse des temps d’exécution des composants les plus gourmands) | G92: Perfectionnement | H92: Programme de formation | J92: J1 | K92: J2·S3 | L92: J2·S3 | M92: J2·S3 | N92: J6 | O92: 5 | R92: NumericTolerance | S92: Exercice Grasshopper | T92: P2
A93: 90 | B93: PRG-027 | C93: 5 – Méthode, performance et évènements | D93: Chronologie et évènements | E93: Ordre d'exécution des tâches | F93: Appréhender la notion d’ordre d’exécution des tâches (Déclencheurs, Timer…) | G93: Perfectionnement | H93: Programme de formation | J93: J1 | K93: J2·S4 | L93: J2·S4 | M93: J2·S4 | N93: J6 | O93: 5 | R93: Conceptuel (QCM) | S93: QCM / question ciblée | T93: P2
A94: 91 | B94: PRG-040 | C94: 5 – Méthode, performance et évènements | D94: Chronologie et évènements | E94: Évènement clavier | F94: Détecter l’appui de l’utilisateur sur une touche du clavier | G94: Perfectionnement | H94: Programme de formation | K94: J2·S4 | L94: J2·S4 | M94: J2·S4 | O94: 3 | R94: Conceptuel (QCM) | S94: Démonstration formateur | T94: P2
A95: 92 | B95: PRG-041 | C95: 5 – Méthode, performance et évènements | D95: Chronologie et évènements | E95: Évènement souris | F95: Détecter le mouvement de la souris | G95: Perfectionnement | H95: Programme de formation | K95: J2·S4 | L95: J2·S4 | M95: J2·S4 | O95: 3 | R95: Conceptuel (QCM) | S95: Démonstration formateur | T95: P2
A96: 93 | B96: PRG-028 | C96: 6 – Algorithmique avancée | D96: Boucles et itération | E96: Boucles et itération | F96: Utilisation des boucles sur groupe de composants avec les plugins Hoopsnake et Anemone | G96: Perfectionnement | H96: Programme de formation | J96: J2 | K96: J3·S5 | L96: J3·S5 | M96: J3·S5 | N96: J7 | O96: 5 | R96: ExactOrderedList | S96: Exercice Grasshopper | T96: P2
A97: 94 | B97: PRG-029 | C97: 6 – Algorithmique avancée | D97: Simulation physique | E97: Simulation physique | F97: Utiliser un moteur physique pour modéliser un phénomène dynamique et trouver un équilibre entre plusieurs contraintes avec Kangaroo | G97: Perfectionnement | H97: Programme de formation | J97: J2 | K97: J3·S5 | L97: J3·S5 | M97: J3·S5 | N97: J7 | O97: 5 | R97: GeometryTolerance | S97: Exercice Grasshopper | T97: P2
A98: 95 | B98: PRG-030 | C98: 6 – Algorithmique avancée | D98: Design génératif | E98: Design génératif | F98: Utiliser un algorithme génétique pour optimiser des variables d’entrée en fonction d’une valeur cible à maximiser ou minimiser avec Galapagos | G98: Perfectionnement | H98: Programme de formation | J98: J2 | K98: J3·S6 | L98: J3·S6 | M98: J3·S6 | N98: J7 | O98: 5 | R98: NumericTolerance | S98: Exercice Grasshopper | T98: P2
A99: 96 | B99: PRG-033 | C99: 7 – Développement, scripting et API | D99: Compilation et IDE | E99: Composant compilé .gha | F99: Comment réaliser un composant *.gha pour Grasshopper | G99: Expert | H99: Programme de formation | J99: J3 | N99: J8 | O99: 2 | R99: Conceptuel (QCM) | S99: Démonstration formateur | T99: P2
A100: 97 | B100: PRG-034 | C100: 7 – Développement, scripting et API | D100: Compilation et IDE | E100: Compilation en plugin .rhp | F100: Comment compiler une définition grasshopper pour en faire un plugin *.rhp de Rhino en utilisant le compilateur de scripts | G100: Expert | H100: Programme de formation | J100: J3 | N100: J8 | O100: 2 | R100: Conceptuel (QCM) | S100: Démonstration formateur | T100: P2
A101: 98 | B101: PRG-047 | C101: 7 – Développement, scripting et API | D101: Compilation et IDE | E101: IDE Visual Studio – templates | F101: Découvrir les templates disponibles sous Visual Studio | G101: Expert | H101: Programme de formation | K101: J4·S8 | L101: J4·S8 | M101: J4·S8 | O101: 3 | R101: Conceptuel (QCM) | S101: Démonstration formateur | T101: P2
A102: 99 | B102: PRG-048 | C102: 7 – Développement, scripting et API | D102: Compilation et IDE | E102: Plugin Rhino en C#.NET | F102: Ecrire un composant plugin de Rhino en C#.NET sous Visual Studio | G102: Expert | H102: Programme de formation | K102: J4·S8 | L102: J4·S8 | M102: J4·S8 | O102: 3 | R102: Conceptuel (QCM) | S102: Démonstration formateur | T102: P2
A103: 100 | B103: PRG-035 | C103: 7 – Développement, scripting et API | D103: Scripting dans Grasshopper | E103: Scripting dans Grasshopper | F103: Ecrire un composant VB / C# / Python personnalisé dans grasshopper | G103: Expert | H103: Programme de formation | J103: J3 | N103: J8 | O103: 2 | R103: SingleValue | S103: Exercice Grasshopper | T103: P2
A104: 101 | B104: PRG-045 | C104: 7 – Développement, scripting et API | D104: Scripting dans Grasshopper | E104: Composant Python | F104: Ecrire un composant Python personnalisé dans grasshopper | G104: Expert | H104: Programme de formation | K104: J4·S8 | L104: J4·S8 | M104: J4·S8 | O104: 3 | R104: SingleValue | S104: Exercice Grasshopper | T104: P2
A105: 102 | B105: PRG-046 | C105: 7 – Développement, scripting et API | D105: Scripting dans Grasshopper | E105: Composant VB / C# | F105: Ecrire un composant VB / C# personnalisé dans grasshopper | G105: Expert | H105: Programme de formation | K105: J4·S8 | L105: J4·S8 | M105: J4·S8 | O105: 3 | R105: SingleValue | S105: Exercice Grasshopper | T105: P2
A106: 103 | B106: PRG-042 | C106: 7 – Développement, scripting et API | D106: API et librairies | E106: API RhinoCommon | F106: Présentation des différentes API Rhinocommon dans l’environnement Rhino dans les différents langages de programmation (Python, C#.NET, VB.NET, etc…) | G106: Expert | H106: Programme de formation | K106: J4·S7 | L106: J4·S7 | M106: J4·S7 | O106: 3 | R106: Conceptuel (QCM) | S106: QCM / question ciblée | T106: P2
A107: 104 | B107: PRG-043 | C107: 7 – Développement, scripting et API | D107: API et librairies | E107: Librairies opensource Rhino | F107: Présentation des librairies opensource de Rhino : openNURBS, Rhino3dm etc… | G107: Expert | H107: Programme de formation | K107: J4·S7 | L107: J4·S7 | M107: J4·S7 | O107: 3 | R107: Conceptuel (QCM) | S107: QCM / question ciblée | T107: P2
A108: 105 | B108: PRG-044 | C108: 7 – Développement, scripting et API | D108: API et librairies | E108: API Grasshopper | F108: API Grasshopper | G108: Expert | H108: Programme de formation | K108: J4·S7 | L108: J4·S7 | M108: J4·S7 | O108: 3 | R108: Conceptuel (QCM) | S108: QCM / question ciblée | T108: P2
A109: 106 | B109: PRG-031 | C109: 8 – Interfaces, web et interopérabilité | D109: Interfaces utilisateur | E109: Interfaçage d'une définition | F109: Interfacer une définition Grasshopper (Remote control panel, Interface WPF/C# dans Rhino…) | G109: Perfectionnement | H109: Programme de formation | J109: J3 | K109: J4·S7 | L109: J4·S7 | M109: J4·S7 | N109: J8 | O109: 5 | R109: Conceptuel (QCM) | S109: Démonstration formateur | T109: P2
A110: 107 | B110: PRG-032 | C110: 8 – Interfaces, web et interopérabilité | D110: Interfaces utilisateur | E110: Intégration dans Rhino | F110: Lier une définition Grasshopper à un bouton de barre d’outil de Rhino | G110: Perfectionnement | H110: Programme de formation | J110: J3 | K110: J4·S7 | L110: J4·S7 | M110: J4·S7 | N110: J8 | O110: 5 | R110: Conceptuel (QCM) | S110: Démonstration formateur | T110: P2
A111: 108 | B111: PRG-054 | C111: 8 – Interfaces, web et interopérabilité | D111: Publication web | E111: Publication web ShapeDiver | F111: Mise en ligne d’une définition Grasshopper avec Shapediver | G111: Perfectionnement | H111: Programme de formation | K111: J5·S10 | L111: J5·S10 | M111: J5·S10 | O111: 3 | R111: Conceptuel (QCM) | S111: Démonstration formateur | T111: P2
A112: 109 | B112: PRG-055 | C112: 8 – Interfaces, web et interopérabilité | D112: Publication web | E112: Téléchargement de modèles 3D | F112: Ajout d’un bouton pour télécharger des modèles 3D | G112: Perfectionnement | H112: Programme de formation | K112: J5·S10 | L112: J5·S10 | M112: J5·S10 | O112: 3 | R112: Conceptuel (QCM) | S112: Démonstration formateur | T112: P2
...

Sheet Fondamentaux V1
A1: Tableau des fondamentaux Magpie V1 – reprise à l'identique (source J. CAROLUS) | H1: Fondamentaux Grasshopper – Ind. A – 25/08/2026
A3: Ordre de dépendance | B3: Catégorie | C3: Notion | D3: Description | E3: ValidationMode suggéré | F3: A réaliser par | G3: Statut | H3: Lien
A4: 1 | B4: Types | C4: Types de base et conversion implicite | D4: Comportement d'un flux de données (Number, Integer, Text, Boolean, Point...) quand il est accepté implicitement par un composant attendant un autre type (ex : slider → integer). | E4: SingleValue
A5: 2 | B5: Types | C5: Échec de conversion et valeurs invalides | D5: Ce qui se produit quand une conversion implicite échoue (texte non numérique vers un input numérique, etc.) : message d'erreur, valeur nulle, composant en échec. | E5: SingleValue
A6: 3 | B6: Listes | C6: Item, liste et indexation (0-based) | D6: Différence entre un item unique et une liste, lecture d'un élément à un index donné (List Item), indexation négative. | E6: SingleValue
A7: 4 | B7: Listes | C7: Longueur et génération de séries | D7: Comptage d'une liste (List Length) et génération de séquences numériques (Series, Range). | E7: ExactOrderedList
A8: 5 | B8: Comportements implicites | C8: Data Matching par défaut (shortest list) | D8: Comportement automatique de Grasshopper quand deux listes de tailles différentes entrent dans un même composant : troncature implicite sur la plus courte. | E8: ExactOrderedList
A9: 6 | B9: Comportements implicites | C9: Data Matching explicite (Longest List, Cross Reference) | D9: Bascule volontaire entre les modes de correspondance (clic droit sur le composant) et conséquences sur le résultat produit. | E9: ExactOrderedList
A10: 7 | B10: Listes | C10: Tri (Sort List, Sort Text) | D10: Réordonnancement d'une liste selon une clé de tri, avec ou sans liste secondaire liée. | E10: ExactOrderedList
A11: 8 | B11: Listes | C11: Filtrage et suppression (Cull Pattern, Dispatch) | D11: Élimination ou séparation d'éléments d'une liste selon un motif booléen répétitif. | E11: SetEquality
A12: 9 | B12: Listes | C12: Décalage et permutation (Shift List, Reverse List) | D12: Rotation, décalage circulaire et inversion de l'ordre des éléments d'une liste. | E12: ExactOrderedList
A13: 10 | B13: Comportements implicites | C13: Valeurs nulles / vides dans une liste | D13: Propagation silencieuse des valeurs null à travers les composants et impact sur les calculs en aval. | E13: SetEquality
A14: 11 | B14: Arbres | C14: Branche et chemin (path) | D14: Structure d'un arbre de données : notion de branche, de chemin ({0;0;1}) et de correspondance avec une liste imbriquée. | E14: SingleValue
A15: 12 | B15: Arbres | C15: Graft et Flatten | D15: Transformation d'une structure de données : éclatement d'une liste en branches individuelles (Graft) et aplatissement d'un arbre en une seule liste (Flatten). | E15: SetEquality
... A22: 19 | B22: Portes logiques | C22: Structure conditionnelle | D22: Utilisation d'une condition pour orienter un résultat ou filtrer une liste (If, Stream Filter, Dispatch piloté par condition). | E22: SetEquality
A24: Légende ValidationMode :
A25: ExactOrderedList — ordre des éléments compte
A26: SetEquality — ordre indifférent, ensemble attendu
A27: SingleValue — une valeur unique attendue
A28: NumericTolerance — valeur numérique avec marge d'erreur
A29: GeometryTolerance — comparaison géométrique avec tolérance

Sheet Contenu programmes
A1: Relevé exhaustif du contenu des programmes de formation (verbatim) | I1: Fondamentaux Grasshopper – Ind. A – 25/08/2026
A3: N° | B3: Code | C3: Programme | D3: Jour | E3: Session | F3: Rubrique | G3: Item (verbatim) | H3: ID référentiel | I3: Domaine | J3: Catégorie
A4: 1 | B4: D3 | C4: Grasshopper débutant 3 jours | D4: Jour 1 | F4: Principes de base de Grasshopper | G4: Introduction à la conception paramétrique avec Grasshopper (Principes de la programmation visuelle) | H4: PRG-001 | I4: 1 – Environnement et principes Grasshopper | J4: Principes et interface Grasshopper
A5: 2 | B5: D3 | C5: Grasshopper débutant 3 jours | D5: Jour 1 | F5: Principes de base de Grasshopper | G5: Interopérabilité entre Grasshopper et Rhino (Bake et Geometry Pipeline) | H5: PRG-002 | I5: 1 – Environnement et principes Grasshopper | J5: Principes et interface Grasshopper
A6: 3 | B6: D3 | C6: Grasshopper débutant 3 jours | D6: Jour 1 | F6: Principes de base de Grasshopper | G6: La logique de Grasshopper (Curseurs, données d’entrée, panel, données de sortie, branchement des câbles… ) | H6: PRG-003 | I6: 1 – Environnement et principes Grasshopper | J6: Principes et interface Grasshopper
A7: 4 | B7: D3 | C7: Grasshopper débutant 3 jours | D7: Jour 1 | F7: Principes de base de Grasshopper | G7: L’environnement et l’interface de Grasshopper (Barre d’outils et navigation dans le Canvas) | H7: PRG-004 | I7: 1 – Environnement et principes Grasshopper | J7: Principes et interface Grasshopper
A8: 5 | B8: D3 | C8: Grasshopper débutant 3 jours | D8: Jour 1 | F8: Géométrie vectorielle et filaire sous Grasshopper | G8: Création d’éléments de construction vectoriels (Points, vecteurs, plans) | H8: PRG-005 | I8: 3 – Géométrie paramétrique | J8: Géométrie vectorielle et filaire
A9: 6 | B9: D3 | C9: Grasshopper débutant 3 jours | D9: Jour 1 | F9: Géométrie vectorielle et filaire sous Grasshopper | G9: Création de géométrie filaire (Cercles, carrés, Polygones, Courbes…) | H9: PRG-006 | I9: 3 – Géométrie paramétrique | J9: Géométrie vectorielle et filaire
A10: 7 | B10: D3 | C10: Grasshopper débutant 3 jours | D10: Jour 1 | F10: Géométrie vectorielle et filaire sous Grasshopper | G10: Les outils de division de courbes | H10: PRG-007 | I10: 3 – Géométrie paramétrique | J10: Géométrie vectorielle et filaire
A11: 8 | B11: D3 | C11: Grasshopper débutant 3 jours | D11: Jour 1 | F11: Plan paramétrique | G11: Exercice d’application sur un dessin paramétrique 2D | H11: PRG-008 | I11: 3 – Géométrie paramétrique | J11: Plan paramétrique
A12: 9 | B12: D3 | C12: Grasshopper débutant 3 jours | D12: Jour 1 | F12: Plan paramétrique | G12: Génération des cotations automatique | H12: PRG-009 | I12: 3 – Géométrie paramétrique | J12: Plan paramétrique
A13: 10 | B13: D3 | C13: Grasshopper débutant 3 jours | D13: Jour 2 | F13: Déplacement et de copie d’objets sous Grasshopper | G13: Les outils de transformation (matrice linéaire, polaire, rotation , symétrie…) | H13: PRG-010 | I13: 3 – Géométrie paramétrique | J13: Transformations et réseaux
A14: 11 | B14: D3 | C14: Grasshopper débutant 3 jours | D14: Jour 2 | F14: Déplacement et de copie d’objets sous Grasshopper | G14: Les matrices rectangulaires et polaires | H14: PRG-011 | I14: 3 – Géométrie paramétrique | J14: Transformations et réseaux
A15: 12 | B15: D3 | C15: Grasshopper débutant 3 jours | D15: Jour 2 | F15: Géométries surfaciques et solides sous Grasshopper | G15: Création de géométrie surfacique (balayage, surface par section…) | H15: PRG-012 | I15: 3 – Géométrie paramétrique | J15: Surfaces et solides
... A38: 35 | B38: P3 | C38: Grasshopper perfectionnement 3 jours | D38: Jour 3 | F38: Codage / programmation | G38: Ecrire un composant VB / C# / Python personnalisé dans grasshopper | H38: PRG-035 | I38: 7 – Développement, scripting et API | J38: Scripting dans Grasshopper
A39: 36 | B39: P6 | C39: Grasshopper perfectionnement 6 jours | D39: Jour 1 | E39: Session N°1 | F39: Gestion des données : utilisation fine des listes et des arbres de données | G39: Outils de traitement des Listes, fonctions de tri par ordre croissant et décroissant | H39: PRG-017 | I39: 2 – Données et logique | J39: Listes
A40: 37 | B40: P6 | C40: Grasshopper perfectionnement 6 jours | D40: Jour 1 | E40: Session N°1 | F40: Gestion des données : utilisation fine des listes et des arbres de données | G40: Création et lecture d’un arbre de données et numérotation des branches | H40: PRG-018 | I40: 2 – Données et logique | J40: Arbres de données
A41: 38 | B41: P6 | C41: Grasshopper perfectionnement 6 jours | D41: Jour 1 | E41: Session N°1 | F41: Gestion des données : utilisation fine des listes et des arbres de données | G41: Approfondir les listes et arbres de données (créer un arbre de données, lire dans un arbre de données, Graft et Flatten) | H41: PRG-024 | I41: 2 – Données et logique | J41: Arbres de données
A42: 39 | B42: P6 | C42: Grasshopper perfectionnement 6 jours | D42: Jour 1 | E42: Session N°1 | F42: Mesures | G42: Outils de mesure (Longueurs, Aires, Volumes) | H42: PRG-019 | I42: 4 – Mesures, quantitatifs et export | J42: Mesures géométriques
A43: 40 | B43: P6 | C43: Grasshopper perfectionnement 6 jours | D43: Jour 1 | E43: Session N°1 | F43: Mesures | G43: Mesure de rayon et courbure | H43: PRG-020 | I43: 4 – Mesures, quantitatifs et export | J43: Mesures géométriques
A44: 41 | B44: P6 | C44: Grasshopper perfectionnement 6 jours | D44: Jour 1 | E44: Session N°1 | F44: Mesures | G44: Recherche d’un centre de gravité | H44: PRG-021 | I44: 4 – Mesures, quantitatifs et export | J44: Mesures géométriques
A45: 42 | B45: P6 | C45: Grasshopper perfectionnement 6 jours | D45: Jour 1 | E45: Session N°1 | F45: Mesures | G45: Comptage automatique des quantités de blocs | H45: PRG-036 | I45: 4 – Mesures, quantitatifs et export | J45: Quantitatifs et chiffrage
A46: 43 | B46: P6 | C46: Grasshopper perfectionnement 6 jours | D46: Jour 1 | E46: Session N°2 | F46: Métrés et chiffrage | G46: Exercice d’application sur un calcul de métrés | H46: PRG-022 | I46: 4 – Mesures, quantitatifs et export | J46: Quantitatifs et chiffrage
A47: 44 | B47: P6 | C47: Grasshopper perfectionnement 6 jours | D47: Jour 1 | E47: Session N°2 | F47: Métrés et chiffrage | G47: Exercice d’application sur un devis généré à partir d’un modèle 3D grasshopper | H47: PRG-023 | I47: 4 – Mesures, quantitatifs et export | J47: Quantitatifs et chiffrage
A48: 45 | B48: P6 | C48: Grasshopper perfectionnement 6 jours | D48: Jour 1 | E48: Session N°2 | F48: Export EXCEL | G48: Préparation des données des colonnes dans Grasshopper | H48: PRG-037 | I48: 4 – Mesures, quantitatifs et export | J48: Export de données
A49: 46 | B49: P6 | C49: Grasshopper perfectionnement 6 jours | D49: Jour 1 | E49: Session N°2 | F49: Export EXCEL | G49: Export d’un tableau de données vers EXCEL dans une feuille de calcul | H49: PRG-038 | I49: 4 – Mesures, quantitatifs et export | J49: Export de données
A50: 47 | B50: P6 | C50: Grasshopper perfectionnement 6 jours | D50: Jour 1 | E50: Session N°2 | F50: Export EXCEL | G50: Export d’une nomenclature au format CSV à partir de Grasshopper | H50: PRG-039 | I50: 4 – Mesures, quantitatifs et export | J50: Export de données
... A178: 175 | B178: P6A | C178: Grasshopper perfectionnement 6 jours – Ind A – 27/02/2025 | D178: Jour 6 | E178: Session N°12 | F178: Déroulé automatique de pièce | G178: Déroulé de tôles en prenant en compte l’épaisseur de la pièce et le retrait | H178: PRG-062 | I178: 9 – Aide à la fabrication | J178: Déroulé et mise à plat
A179: 176 | B179: RG8 | C179: Rhino – Grasshopper 8 jours | D179: Jour 1 | F179: Les Fondamentaux de Rhino | G179: Présentation de l'interface utilisateur (barres d’outils, fenêtres, options). | H179: PRG-074 | I179: 0 – Socle Rhino (prérequis) | J179: Interface et navigation Rhino
A180: 177 | B180: RG8 | C180: Rhino – Grasshopper 8 jours | D180: Jour 1 | F180: Les Fondamentaux de Rhino | G180: Manipulation des vues | H180: PRG-075 | I180: 0 – Socle Rhino (prérequis) | J180: Interface et navigation Rhino
A181: 178 | B181: RG8 | C181: Rhino – Grasshopper 8 jours | D181: Jour 1 | F181: Les Fondamentaux de Rhino | G181: Outils de navigation : zoom, panoramique, rotation. | H181: PRG-076 | I181: 0 – Socle Rhino (prérequis) | J181: Interface et navigation Rhino
A182: 179 | B182: RG8 | C182: Rhino – Grasshopper 8 jours | D182: Jour 1 | F182: Les Fondamentaux de Rhino | G182: Création et manipulation d'objets de base (cubes, sphères, cylindres, etc.). | H182: PRG-077 | I182: 0 – Socle Rhino (prérequis) | J182: Modélisation Rhino
A183: 180 | B183: RG8 | C183: Rhino – Grasshopper 8 jours | D183: Jour 1 | F183: Les Fondamentaux de Rhino | G183: Transformation de base : déplacer, tourner, échelle, orienter | H183: PRG-078 | I183: 0 – Socle Rhino (prérequis) | J183: Modélisation Rhino
A184: 181 | B184: RG8 | C184: Rhino – Grasshopper 8 jours | D184: Jour 1 | F184: Les Fondamentaux de Rhino | G184: Sélection et manipulation d’objets | H184: PRG-079 | I184: 0 – Socle Rhino (prérequis) | J184: Interface et navigation Rhino
A185: 182 | B185: RG8 | C185: Rhino – Grasshopper 8 jours | D185: Jour 1 | F185: Les Fondamentaux de Rhino | G185: Groupes et blocs | H185: PRG-080 | I185: 0 – Socle Rhino (prérequis) | J185: Interface et navigation Rhino
A186: 183 | B186: RG8 | C186: Rhino – Grasshopper 8 jours | D186: Jour 1 | F186: Les Fondamentaux de Rhino | G186: Verrouillage et masquage d’objets, Isoler, Montrer) | H186: PRG-081 | I186: 0 – Socle Rhino (prérequis) | J186: Interface et navigation Rhino
A187: 184 | B187: RG8 | C187: Rhino – Grasshopper 8 jours | D187: Jour 1 | F187: Les Fondamentaux de Rhino | G187: Création de courbes de différentes formes (lignes, cercles, ellipses, etc.). | H187: PRG-082 | I187: 0 – Socle Rhino (prérequis) | J187: Modélisation Rhino
A188: 185 | B188: RG8 | C188: Rhino – Grasshopper 8 jours | D188: Jour 1 | F188: Les Fondamentaux de Rhino | G188: Utilisation de l’outil de courbes pour générer des surfaces. | H188: PRG-083 | I188: 0 – Socle Rhino (prérequis) | J188: Modélisation Rhino
A189: 186 | B189: RG8 | C189: Rhino – Grasshopper 8 jours | D189: Jour 1 | F189: Les Fondamentaux de Rhino | G189: Extrusion et création de surfaces à partir de courbes. | H189: PRG-084 | I189: 0 – Socle Rhino (prérequis) | J189: Modélisation Rhino
A190: 187 | B190: RG8 | C190: Rhino – Grasshopper 8 jours | D190: Jour 1 | F190: Les Fondamentaux de Rhino | G190: Opérations booléennes (Union, intersection, et soustraction) | H190: PRG-085 | I190: 0 – Socle Rhino (prérequis) | J190: Modélisation Rhino
... A237: 234 | B237: RG8 | C237: Rhino – Grasshopper 8 jours | D237: Jour 8 | F237: Codage / Programmation | G237: Ecrire un composant VB / C# / Python personnalisé dans grasshopper | H237: PRG-035 | I237: 7 – Développement, scripting et API | J237: Scripting dans Grasshopper

Sheet Synthèse
A1: Synthèse et analyse des écarts | F1: Fondamentaux Grasshopper – Ind. A – 25/08/2026
A3: Répartition par domaine
A4: Domaine | B4: Notions | C4: dont issues des programmes | D4: dont priorité P0
A5: 0 – Socle Rhino (prérequis) | B5: =COUNTIF(Référentiel!$C$4:$C$119,$A5) -> 24 | C5: =COUNTIFS(Référentiel!$C$4:$C$119,$A5,Référentiel!$H$4:$H$119,"Programme de formation") -> 24 | D5: =COUNTIFS(Référentiel!$C$4:$C$119,$A5,Référentiel!$S$4:$S$119,"P0") -> 0
A6: 1 – Environnement et principes Grasshopper | B6: =COUNTIF(Référentiel!$C$4:$C$119,$A6) -> 15 | C6: =COUNTIFS(Référentiel!$C$4:$C$119,$A6,Référentiel!$H$4:$H$119,"Programme de formation") -> 15 | D6: =COUNTIFS(Référentiel!$C$4:$C$119,$A6,Référentiel!$S$4:$S$119,"P0") -> 0
A7: 2 – Données et logique | B7: =COUNTIF(Référentiel!$C$4:$C$119,$A7) -> 22 | C7: =COUNTIFS(Référentiel!$C$4:$C$119,$A7,Référentiel!$H$4:$H$119,"Programme de formation") -> 3 | D7: =COUNTIFS(Référentiel!$C$4:$C$119,$A7,Référentiel!$S$4:$S$119,"P0") -> 0
A8: 3 – Géométrie paramétrique | B8: =COUNTIF(Référentiel!$C$4:$C$119,$A8) -> 17 | C8: =COUNTIFS(Référentiel!$C$4:$C$119,$A8,Référentiel!$H$4:$H$119,"Programme de formation") -> 17 | D8: =COUNTIFS(Référentiel!$C$4:$C$119,$A8,Référentiel!$S$4:$S$119,"P0") -> 0
A9: 4 – Mesures, quantitatifs et export | B9: =COUNTIF(Référentiel!$C$4:$C$119,$A9) -> 9 | C9: =COUNTIFS(Référentiel!$C$4:$C$119,$A9,Référentiel!$H$4:$H$119,"Programme de formation") -> 9 | D9: =COUNTIFS(Référentiel!$C$4:$C$119,$A9,Référentiel!$S$4:$S$119,"P0") -> 0
A10: 5 – Méthode, performance et évènements | B10: =COUNTIF(Référentiel!$C$4:$C$119,$A10) -> 5 | C10: =COUNTIFS(Référentiel!$C$4:$C$119,$A10,Référentiel!$H$4:$H$119,"Programme de formation") -> 5 | D10: =COUNTIFS(Référentiel!$C$4:$C$119,$A10,Référentiel!$S$4:$S$119,"P0") -> 0
A11: 6 – Algorithmique avancée | B11: =COUNTIF(Référentiel!$C$4:$C$119,$A11) -> 3 | C11: =COUNTIFS(Référentiel!$C$4:$C$119,$A11,Référentiel!$H$4:$H$119,"Programme de formation") -> 3 | D11: =COUNTIFS(Référentiel!$C$4:$C$119,$A11,Référentiel!$S$4:$S$119,"P0") -> 0
A12: 7 – Développement, scripting et API | B12: =COUNTIF(Référentiel!$C$4:$C$119,$A12) -> 10 | C12: =COUNTIFS(Référentiel!$C$4:$C$119,$A12,Référentiel!$H$4:$H$119,"Programme de formation") -> 10 | D12: =COUNTIFS(Référentiel!$C$4:$C$119,$A12,Référentiel!$S$4:$S$119,"P0") -> 0
A13: 8 – Interfaces, web et interopérabilité | B13: =COUNTIF(Référentiel!$C$4:$C$119,$A13) -> 7 | C13: =COUNTIFS(Référentiel!$C$4:$C$119,$A13,Référentiel!$H$4:$H$119,"Programme de formation") -> 7 | D13: =COUNTIFS(Référentiel!$C$4:$C$119,$A13,Référentiel!$S$4:$S$119,"P0") -> 0
A14: 9 – Aide à la fabrication | B14: =COUNTIF(Référentiel!$C$4:$C$119,$A14) -> 4 | C14: =COUNTIFS(Référentiel!$C$4:$C$119,$A14,Référentiel!$H$4:$H$119,"Programme de formation") -> 4 | D14: =COUNTIFS(Référentiel!$C$4:$C$119,$A14,Référentiel!$S$4:$S$119,"P0") -> 0
A16: Répartition par niveau
A17: Niveau | B17: Notions
A18: Débutant | B18: =COUNTIF(Référentiel!$G$4:$G$119,$A18) -> 50
A19: Intermédiaire | B19: =COUNTIF(Référentiel!$G$4:$G$119,$A19) -> 33
A20: Perfectionnement | B20: =COUNTIF(Référentiel!$G$4:$G$119,$A20) -> 21
A21: Expert | B21: =COUNTIF(Référentiel!$G$4:$G$119,$A21) -> 12
A23: Répartition par mode de validation
A24: ValidationMode | B24: Notions
A25: ExactOrderedList | B25: =COUNTIF(Référentiel!$R$4:$R$119,$A25) -> 8
A26: SetEquality | B26: =COUNTIF(Référentiel!$R$4:$R$119,$A26) -> 9
A27: SingleValue | B27: =COUNTIF(Référentiel!$R$4:$R$119,$A27) -> 18
A28: NumericTolerance | B28: =COUNTIF(Référentiel!$R$4:$R$119,$A28) -> 8
A29: GeometryTolerance | B29: =COUNTIF(Référentiel!$R$4:$R$119,$A29) -> 26
A30: Conceptuel (QCM) | B30: =COUNTIF(Référentiel!$R$4:$R$119,$A30) -> 46
A32: Répartition par type d'exercice
A33: Type d'exercice | B33: Notions
A34: Exercice Grasshopper | B34: =COUNTIF(Référentiel!$S$4:$S$119,$A34) -> 66
A35: Exercice de synthèse | B35: =COUNTIF(Référentiel!$S$4:$S$119,$A35) -> 4
A36: QCM / question ciblée | B36: =COUNTIF(Référentiel!$S$4:$S$119,$A36) -> 22
A37: Démonstration formateur | B37: =COUNTIF(Référentiel!$S$4:$S$119,$A37) -> 24
A39: Couverture par programme
A40: Programme | B40: Items relevés (verbatim) | C40: Notions distinctes
A41: Grasshopper débutant 3 jours | B41: 23 | C41: =COUNTIF(Référentiel!$I$4:$I$119,"<>") -> 23
A42: Grasshopper perfectionnement 3 jours | B42: 12 | C42: =COUNTIF(Référentiel!$J$4:$J$119,"<>") -> 12
A43: Grasshopper perfectionnement 6 jours | B43: 43 | C43: =COUNTIF(Référentiel!$K$4:$K$119,"<>") -> 43
A44: Grasshopper perfectionnement 6 jours (1) | B44: 43 | C44: =COUNTIF(Référentiel!$L$4:$L$119,"<>") -> 43
A45: Grasshopper perfectionnement 6 jours – Ind A – 27/02/2025 | B45: 54 | C45: =COUNTIF(Référentiel!$M$4:$M$119,"<>") -> 54
A46: Rhino – Grasshopper 8 jours | B46: 59 | C46: =COUNTIF(Référentiel!$N$4:$N$119,"<>") -> 59
A48: Écarts – fondamentaux Magpie V1 face aux programmes
A49: Situation | B49: Nombre
A50: Notion V1 couverte par un item de programme | B50: 4
A51: Notion V1 couverte partiellement | B51: 5
A52: Notion V1 absente des programmes | B52: 10
A54: Détail des notions V1 absentes des programmes de formation
A55: ID | B55: Catégorie | C55: Notion | D55: Niveau | E55: ValidationMode
A56: FND-01 | B56: Types et conversion implicite | C56: Types de base et conversion implicite | D56: Débutant | E56: SingleValue
A57: FND-02 | B57: Types et conversion implicite | C57: Échec de conversion et valeurs invalides | D57: Intermédiaire | E57: SingleValue
A58: FND-05 | B58: Comportements implicites | C58: Data Matching par défaut (shortest list) | D58: Intermédiaire | E58: ExactOrderedList
A59: FND-06 | B59: Comportements implicites | C59: Data Matching explicite (Longest List, Cross Reference) | D59: Intermédiaire | E59: ExactOrderedList
A60: FND-10 | B60: Comportements implicites | C60: Valeurs nulles / vides dans une liste | D60: Intermédiaire | E60: SetEquality
A61: FND-15 | B61: Outils de texte | C61: Concaténation et construction de chaînes | D61: Débutant | E61: SingleValue
A62: FND-16 | B62: Outils de texte | C62: Manipulation de texte | D62: Intermédiaire | E62: SingleValue
A63: FND-17 | B63: Portes logiques | C63: Booléens et comparaisons | D63: Débutant | E63: SingleValue
A64: FND-18 | B64: Portes logiques | C64: Opérateurs logiques combinés | D64: Intermédiaire | E64: SingleValue
A65: FND-19 | B65: Portes logiques | C65: Structure conditionnelle | D65: Intermédiaire | E65: SetEquality

Sheet Listes
A1: Listes de valeurs | F1: Fondamentaux Grasshopper – Ind. A – 25/08/2026
A3: Domaines | B3: Niveaux | C3: ValidationMode | D3: Types d'exercice | E3: Priorités | F3: Statuts
A4: 0 – Socle Rhino (prérequis) | B4: Débutant | C4: ExactOrderedList | D4: Exercice Grasshopper | E4: P0 | F4: Pas commencé
A5: 1 – Environnement et principes Grasshopper | B5: Intermédiaire | C5: SetEquality | D5: Exercice de synthèse | E5: P1 | F5: En cours
A6: 2 – Données et logique | B6: Perfectionnement | C6: SingleValue | D6: QCM / question ciblée | E6: P2 | F6: Terminé
A7: 3 – Géométrie paramétrique | B7: Expert | C7: NumericTolerance | D7: Démonstration formateur | F7: Bloqué
A8: 4 – Mesures, quantitatifs et export | C8: GeometryTolerance
A9: 5 – Méthode, performance et évènements | C9: Conceptuel (QCM)
A10: 6 – Algorithmique avancée
A11: 7 – Développement, scripting et API
A12: 8 – Interfaces, web et interopérabilité
A13: 9 – Aide à la fabrication
